ggca-1.0.1.dist-info/METADATA
ggca-1.0.1.dist-info/WHEEL
ggca-1.0.1.dist-info/licenses/LICENSE
ggca/__init__.py
ggca/__init__.pyi
ggca/py.typed
ggca/ggca.cp38-win32.pyd
ggca-1.0.1.dist-info/RECORD
