Metadata-Version: 2.3
Name: ggca
Version: 1.0.1
Classifier: Topic :: Scientific/Engineering :: Bio-Informatics
Classifier: Programming Language :: Rust
Classifier: Programming Language :: Python
License-File: LICENSE
Summary: Computes efficiently the correlation (Pearson, Spearman or Kendall) and the p-value (two-sided) between all the pairs from two datasets
Keywords: mRNA,expression,modulation,correlation,p-value
Author: JWare Solutions <jware.organization@gmail.com>, Sergio Leandro Calderón <bs.sergiocalderon@gmail.com>
Author-email: JWare Solutions <jware.organization@gmail.com>, Sergio Leandro Calderón <bs.sergiocalderon@gmail.com>
License: MIT
Requires-Python: >=3.6
Project-URL: Source Code, https://github.com/jware-solutions/ggca
